{
  "Datos": [
    {
      "Maquina": "app-server",
      "Fecha": "2020/06/14 19:32:24",
      "tcpInSegs": "27",
      "tcpOutSegs": "33",
      "udpInSegs": "54",
      "udpOutSegs": "95",
      "upTime": "0:01:21.81"
    },
    {
      "Maquina": "app-server",
      "Fecha": "2020/06/14 19:32:29",
      "tcpInSegs": "27",
      "tcpOutSegs": "33",
      "udpInSegs": "66",
      "udpOutSegs": "107",
      "upTime": "0:01:26.95"
    },
    {
      "Maquina": "app-server",
      "Fecha": "2020/06/14 19:32:34",
      "tcpInSegs": "27",
      "tcpOutSegs": "33",
      "udpInSegs": "78",
      "udpOutSegs": "119",
      "upTime": "0:01:32.22"
    },
    {
      "Maquina": "app-server",
      "Fecha": "2020/06/14 19:32:39",
      "tcpInSegs": "27",
      "tcpOutSegs": "33",
      "udpInSegs": "90",
      "udpOutSegs": "131",
      "upTime": "0:01:37.33"
    },
    {
      "Maquina": "app-server",
      "Fecha": "2020/06/14 19:44:48",
      "tcpInSegs": "49",
      "tcpOutSegs": "55",
      "udpInSegs": "105",
      "udpOutSegs": "146",
      "upTime": "0:13:46.24"
    },
    {
      "Maquina": "app-server",
      "Fecha": "2020/06/14 19:44:53",
      "tcpInSegs": "49",
      "tcpOutSegs": "55",
      "udpInSegs": "117",
      "udpOutSegs": "158",
      "upTime": "0:13:51.34"
    },
    {
      "Maquina": "app-server",
      "Fecha": "2020/06/14 19:44:58",
      "tcpInSegs": "49",
      "tcpOutSegs": "55",
      "udpInSegs": "129",
      "udpOutSegs": "170",
      "upTime": "0:13:56.44"
    },
    {
      "Maquina": "app-server",
      "Fecha": "2020/06/14 19:45:03",
      "tcpInSegs": "49",
      "tcpOutSegs": "55",
      "udpInSegs": "141",
      "udpOutSegs": "182",
      "upTime": "0:14:01.54"
    },
    {
      "Maquina": "app-server",
      "Fecha": "2020/06/14 19:45:08",
      "tcpInSegs": "49",
      "tcpOutSegs": "55",
      "udpInSegs": "153",
      "udpOutSegs": "194",
      "upTime": "0:14:06.65"
    },
    {
      "Maquina": "app-server",
      "Fecha": "2020/06/14 19:45:14",
      "tcpInSegs": "49",
      "tcpOutSegs": "55",
      "udpInSegs": "165",
      "udpOutSegs": "206",
      "upTime": "0:14:11.75"
    },
    {
      "Maquina": "app-server",
      "Fecha": "2020/06/14 19:45:19",
      "tcpInSegs": "49",
      "tcpOutSegs": "55",
      "udpInSegs": "177",
      "udpOutSegs": "218",
      "upTime": "0:14:16.85"
    },
    {
      "Maquina": "app-server",
      "Fecha": "2020/06/14 19:45:24",
      "tcpInSegs": "49",
      "tcpOutSegs": "55",
      "udpInSegs": "189",
      "udpOutSegs": "230",
      "upTime": "0:14:21.95"
    }
  ]
}
